ExcelCSVParseHelper/__init__.py
ExcelCSVParseHelper/core.py
excelcsvparsehelper-1.2.3.dist-info/licenses/LICENSE
excelcsvparsehelper-1.2.3.dist-info/METADATA
excelcsvparsehelper-1.2.3.dist-info/WHEEL
excelcsvparsehelper-1.2.3.dist-info/top_level.txt
excelcsvparsehelper-1.2.3.dist-info/RECORD
