Metadata-Version: 2.4
Name: ExcelCSVParseHelper
Version: 1.2.3
Summary: Lightweight helper library for parsing and manipulating Excel and CSV files easily.
Author: Marcin Kowalczyk
Classifier: Programming Language :: Python :: 3
Classifier: Programming Language :: Python :: 3 :: Only
Classifier: Operating System :: OS Independent
Classifier: Operating System :: Microsoft :: Windows
Classifier: Operating System :: MacOS
Classifier: Operating System :: POSIX :: Linux
Requires-Python: >=3.10
License-File: LICENSE
Requires-Dist: pandas>=2.0
Requires-Dist: openpyxl>=3.1.5
Requires-Dist: LockFileSemaphore>=3.0.2
Requires-Dist: psutil; platform_system == "Windows"
Requires-Dist: pywin32; platform_system == "Windows"
Dynamic: author
Dynamic: classifier
Dynamic: description
Dynamic: description-content-type
Dynamic: license-file
Dynamic: requires-dist
Dynamic: requires-python
Dynamic: summary
